amostra/__init__.py
amostra/_version.py
amostra/handlers.py
amostra/http_client.py
amostra/mongo_client.py
amostra/objects.py
amostra/server.py
amostra/utils.py
amostra/schemas/container.json
amostra/schemas/institution.json
amostra/schemas/owner.json
amostra/schemas/project.json
amostra/schemas/sample.json
amostra/tests/__init__.py
amostra/tests/conftest.py
amostra/tests/test_examples.py
amostra/tests/test_revert.py
amostra-1.0.1.dist-info/METADATA
amostra-1.0.1.dist-info/RECORD
amostra-1.0.1.dist-info/WHEEL
amostra-1.0.1.dist-info/entry_points.txt
amostra-1.0.1.dist-info/top_level.txt
